{
  "id": "2857857",
  "name": "美团",
  "font_family": "iconfont",
  "css_prefix_text": "icon-",
  "description": "",
  "glyphs": [
    {
      "icon_id": "2310975",
      "name": "篮球",
      "font_class": "lanqiu",
      "unicode": "e645",
      "unicode_decimal": 58949
    },
    {
      "icon_id": "3789402",
      "name": "电影",
      "font_class": "dianying",
      "unicode": "e620",
      "unicode_decimal": 58912
    },
    {
      "icon_id": "3858935",
      "name": "品味生活",
      "font_class": "pinweishenghuo",
      "unicode": "e66d",
      "unicode_decimal": 58989
    },
    {
      "icon_id": "3873062",
      "name": "丽人",
      "font_class": "icon-test",
      "unicode": "e654",
      "unicode_decimal": 58964
    },
    {
      "icon_id": "3885962",
      "name": "酒吧",
      "font_class": "_jiuba",
      "unicode": "e825",
      "unicode_decimal": 59429
    },
    {
      "icon_id": "5055076",
      "name": "发起培训",
      "font_class": "faqipeixun",
      "unicode": "e62b",
      "unicode_decimal": 58923
    },
    {
      "icon_id": "5207075",
      "name": "酒店",
      "font_class": "jiudian",
      "unicode": "e642",
      "unicode_decimal": 58946
    },
    {
      "icon_id": "5484495",
      "name": "机票",
      "font_class": "jipiao",
      "unicode": "e7b3",
      "unicode_decimal": 59315
    },
    {
      "icon_id": "6331599",
      "name": "美食",
      "font_class": "meishi",
      "unicode": "e631",
      "unicode_decimal": 58929
    },
    {
      "icon_id": "9073973",
      "name": "2_7休闲娱乐",
      "font_class": "_xiuxianyule",
      "unicode": "e619",
      "unicode_decimal": 58905
    },
    {
      "icon_id": "9074025",
      "name": "2_3家装设计",
      "font_class": "_jiazhuangsheji",
      "unicode": "e621",
      "unicode_decimal": 58913
    },
    {
      "icon_id": "15343577",
      "name": "亲子游",
      "font_class": "qinziyou",
      "unicode": "e61a",
      "unicode_decimal": 58906
    },
    {
      "icon_id": "17541945",
      "name": "民宿",
      "font_class": "minsu",
      "unicode": "edfa",
      "unicode_decimal": 60922
    },
    {
      "icon_id": "18267964",
      "name": "医疗机构",
      "font_class": "yiliaojigou",
      "unicode": "e99a",
      "unicode_decimal": 59802
    },
    {
      "icon_id": "21787513",
      "name": "结婚登记",
      "font_class": "jiehundengji",
      "unicode": "e696",
      "unicode_decimal": 59030
    },
    {
      "icon_id": "24111544",
      "name": "外卖",
      "font_class": "waimai",
      "unicode": "fac1",
      "unicode_decimal": 64193
    }
  ]
}
